emu/__init__.py
emu/algorithm.py
emu/functions.py
emu/main.py
emu/memory.cpython-311-darwin.so
emu/shared.cpython-311-darwin.so
emu_popgen-1.1.dist-info/LICENSE
emu_popgen-1.1.dist-info/METADATA
emu_popgen-1.1.dist-info/WHEEL
emu_popgen-1.1.dist-info/entry_points.txt
emu_popgen-1.1.dist-info/top_level.txt
emu_popgen-1.1.dist-info/RECORD
